{
    "Studentname" : [
            {
                "name" : "Username1",
                "age" : 25
            },
            {
                "name" : "Username2",
                "age" : 20
            },
            {
                "name" : "Username3",
                "age" : 21
            },
            {
                "name" : "Username4",
                "age" : 22
            },
            {
                "name" : "Username5",
                "age" : 21
            }
    ]
}